{
	"entries": [
		{
				"message": "Running Enter Site.script",
				"identifier": "START",
				"timestamp": "2024-03-18 11:54:30.427 -0400"
			},
		{
				"handlerName": "on_enter_site",
				"timestamp": "2024-03-18 11:54:30.675 -0400",
				"scriptName": "Enter Site.script",
				"message": "at (39, 287)",
				"image": "chrome_icon",
				"handlerLine": 8,
				"identifier": "doubleclick"
			},
		{
				"handlerName": "on_enter_site",
				"timestamp": "2024-03-18 11:54:35.270 -0400",
				"scriptName": "Enter Site.script",
				"message": "at (135, 63)",
				"image": "magnifying_glass",
				"handlerLine": 9,
				"identifier": "click"
			},
		{
				"handlerName": "on_enter_site",
				"timestamp": "2024-03-18 11:54:36.766 -0400",
				"message": "nopcommerce.testplant.com[return]",
				"scriptName": "Enter Site.script",
				"handlerLine": 10,
				"identifier": "typetext"
			},
		{
				"message": "(Duration:\"6.366\", Errors:\"0\", Exceptions:\"0\", StartTime:\"2024-03-18 11:54:30 -0400\", Successes:\"1\", TestCase:\"Enter Site.script\", Warnings:\"0\")",
				"identifier": "EndTestCase",
				"timestamp": "2024-03-18 11:54:36.798 -0400"
			},
		{
				"message": "Execution Time 0:00:06 Enter Site.script",
				"identifier": "SUCCESS",
				"timestamp": "2024-03-18 11:54:36.827 -0400"
			}
	],
	"createdTimestamp": "2024-03-18 11:54:30.430 -0400"
}